nbdev_pilot_ds_project/__init__.py
nbdev_pilot_ds_project/_modidx.py
nbdev_pilot_ds_project/bloomf.py
nbdev_pilot_ds_project/trie.py
nbdev_pilot_ds_project-0.0.1.dist-info/LICENSE
nbdev_pilot_ds_project-0.0.1.dist-info/METADATA
nbdev_pilot_ds_project-0.0.1.dist-info/WHEEL
nbdev_pilot_ds_project-0.0.1.dist-info/entry_points.txt
nbdev_pilot_ds_project-0.0.1.dist-info/top_level.txt
nbdev_pilot_ds_project-0.0.1.dist-info/RECORD
